{
    "Networks":{
        "url":"",
        "hasChanged":false,
        "snip":{
            "url":"mongodb+srv://dotcode:<password>@snip.ugqc69m.mongodb.net/?retryWrites=true&w=majority",
            "hasChanged":false
        }
    },
    "appSettings":{},
    "app":{
        "version":"",
        "appId":"",
        "apptoken":""
    },
    "system":{
        "Name":"",
        "userinfo":"",
        "version":"",
        "operatingSystem":"",
        "opVersion":"",
        "specifications":{
            "memory":"",
            "freeMemory":"",
            "disc":"",
            "processor":"",
            "arch":"",
            "graphics":""
        },
        "screen":""
    },
    "account":{
        "username":"",
        "password":"",
        "isVerified":true
    },
    "updates":{},
    "time":""
}